inject_config/__init__.py
inject_config/inject_config.py
inject_config-1.0.3.dist-info/METADATA
inject_config-1.0.3.dist-info/WHEEL
inject_config-1.0.3.dist-info/RECORD
