Metadata-Version: 2.1
Name: inject-config
Version: 1.0.3
Summary: Small Config Injection package
License: LICENCE
Author: ahartlba
Author-email: sorry@nomail.com
Requires-Python: >=3.8.1,<4.0.0
Classifier: License :: Other/Proprietary License
Classifier: Programming Language :: Python :: 3
Classifier: Programming Language :: Python :: 3.9
Classifier: Programming Language :: Python :: 3.10
Classifier: Programming Language :: Python :: 3.11
Requires-Dist: pyyaml (>=6.0.1,<7.0.0)
